glover/__init__.py
glover/views.py
glover/render/__init__.py
glover/render/_factory.py
glover/render/morphology.py
glover/render/network.py
glover/render/voxelset.py
glover-0.1.dist-info/WHEEL
glover-0.1.dist-info/METADATA
glover-0.1.dist-info/RECORD
